uniguide_locator/__init__.py
uniguide_locator/locator.py
unimed_guide_locator-0.1.0.dist-info/LICENSE
unimed_guide_locator-0.1.0.dist-info/METADATA
unimed_guide_locator-0.1.0.dist-info/WHEEL
unimed_guide_locator-0.1.0.dist-info/RECORD
