Metadata-Version: 2.1
Name: unimed-guide-locator
Version: 0.1.0
Summary: Guide information gettering for Unimed and Intermed
License: APL 3
Author: Iranildo Alves
Author-email: 117860354+IranTheCreator@users.noreply.github.com
Requires-Python: >=3.11,<4.0
Classifier: License :: Other/Proprietary License
Classifier: Programming Language :: Python :: 3
Classifier: Programming Language :: Python :: 3.11
